binance_trade/__init__.py
binance_trade/utils.py
binance_trade/binance_cm/__init__.py
binance_trade/binance_cm/account/__init__.py
binance_trade/binance_cm/market/__init__.py
binance_trade/binance_cm/trade/__init__.py
binance_trade/binance_cm/trade/_base.py
binance_trade/binance_cm/trade/close.py
binance_trade/binance_cm/trade/open.py
binance_trade/binance_cm/trade/order.py
binance_trade/binance_cm/trade/quantity_and_price.py
binance_trade/binance_spot/__init__.py
binance_trade/binance_spot/account/__init__.py
binance_trade/binance_spot/market/__init__.py
binance_trade/binance_spot/trade/__init__.py
binance_trade/binance_spot/trade/_base.py
binance_trade/binance_spot/trade/close.py
binance_trade/binance_spot/trade/open.py
binance_trade/binance_spot/trade/order.py
binance_trade/binance_spot/trade/quantity_and_price.py
binance_trade/binance_um/__init__.py
binance_trade/binance_um/account/__init__.py
binance_trade/binance_um/market/__init__.py
binance_trade/binance_um/trade/__init__.py
binance_trade/binance_um/trade/_base.py
binance_trade/binance_um/trade/close.py
binance_trade/binance_um/trade/open.py
binance_trade/binance_um/trade/order.py
binance_trade/binance_um/trade/quantity_and_price.py
binance_trade/code/__init__.py
binance_trade/code/account.py
binance_trade/code/execute.py
binance_trade/code/market.py
binance_trade/code/trade.py
binance_trade/exception/__init__.py
binance_trade/exception/_base.py
binance_trade/exception/param.py
binance_trade/exception/req.py
binance_trade/exception/rule.py
binance_trade-1.0.4.dist-info/METADATA
binance_trade-1.0.4.dist-info/WHEEL
binance_trade-1.0.4.dist-info/top_level.txt
binance_trade-1.0.4.dist-info/RECORD
