Metadata-Version: 2.1
Name: binance-trade
Version: 1.0.4
Summary: Make Binance API Transactions Easier
Home-page: https://github.com/pyted/binance_trade
Author: pyted
Author-email: pyted@outlook.com
License: MIT
Classifier: License :: OSI Approved :: MIT License
Classifier: Programming Language :: Python
Classifier: Programming Language :: Python :: 3
Classifier: Programming Language :: Python :: 3.6
Classifier: Programming Language :: Python :: Implementation :: CPython
Classifier: Programming Language :: Python :: Implementation :: PyPy
Requires-Python: >=3.6.0
Requires-Dist: candlelite
Requires-Dist: pbinance
Requires-Dist: binance-candle (>=1.0.3)
Requires-Dist: paux
